astrodash/__init__.py
astrodash/analyse_all_ozdes_atels.py
astrodash/analyse_all_ozdes_atels_combined_fits.py
astrodash/array_tools.py
astrodash/calculate_redshift.py
astrodash/classify.py
astrodash/classify_DES_Y4_spectra_DASH.py
astrodash/classify_OzDES_ATELs.py
astrodash/classify_OzDES_run30.py
astrodash/classify_OzDES_runs.py
astrodash/combine_sn_and_host.py
astrodash/convert_data_to_fits.py
astrodash/create_and_save_all_data_files.py
astrodash/create_arrays.py
astrodash/create_arrays_with_memory_mapping.py
astrodash/create_template_set.py
astrodash/create_training_set.py
astrodash/dash_on_ozdes.py
astrodash/deep_learning_multilayer.py
astrodash/design.py
astrodash/download_data_files.py
astrodash/download_from_ATC.py
astrodash/false_positive_rejection.py
astrodash/gui_main.py
astrodash/helpers.py
astrodash/input_spectra.py
astrodash/model_metrics.py
astrodash/multilayer_convnet.py
astrodash/preprocessing.py
astrodash/read_binned_templates.py
astrodash/read_from_catalog.py
astrodash/restore_model.py
astrodash/save_binned_templates_as_arrays.py
astrodash/sn_processing.py
astrodash/template_files_to_arrays.py
astrodash/test_OzDES_spectra.py
astrodash/test_dash.py
astrodash/training_parameters.py
astrodash/unzip_data_files.py
astrodash-1.0.22.dist-info/LICENCE
astrodash-1.0.22.dist-info/METADATA
astrodash-1.0.22.dist-info/WHEEL
astrodash-1.0.22.dist-info/entry_points.txt
astrodash-1.0.22.dist-info/top_level.txt
astrodash-1.0.22.dist-info/RECORD
