Metadata-Version: 2.1
Name: astrodash
Version: 1.0.22
Summary: Deep Learning for Automated Spectral Classification of Supernovae
Home-page: https://github.com/daniel-muthukrishna/DASH
Author: Daniel Muthukrishna
Author-email: daniel.muthukrishna@gmail.com
License: MIT
Keywords: supernova spectral classification deep machine learning
Platform: UNKNOWN
Classifier: Development Status :: 4 - Beta
Classifier: Intended Audience :: Science/Research
Classifier: Topic :: Scientific/Engineering :: Astronomy
Classifier: License :: OSI Approved :: MIT License
Classifier: Programming Language :: Python :: 2
Classifier: Programming Language :: Python :: 3
Requires-Dist: numpy
Requires-Dist: scipy
Requires-Dist: tensorflow
Requires-Dist: pyqtgraph
Requires-Dist: astropy
